Metadata-Version: 2.1
Name: mlinstrumentation
Version: 0.1.1
Summary: Project for instrumenting Machine Learning python code
Home-page: https://github.com/pypa/sampleproject
Author: The ML instrumentation
Author-email: kerastelemetery@gmail.com
License: UNKNOWN
Project-URL: Source, https://github.com/pypa/sampleproject/
Project-URL: Say Thanks!, http://saythanks.io/to/example
Project-URL: Funding, https://donate.pypi.org
Project-URL: Bug Reports, https://github.com/pypa/sampleproject/issues
Keywords: machine learning instrumentation development
Platform: UNKNOWN
Classifier: Development Status :: 3 - Alpha
Classifier: Intended Audience :: Developers
Classifier: Topic :: Software Development :: Build Tools
Classifier: License :: OSI Approved :: MIT License
Classifier: Programming Language :: Python :: 2
Classifier: Programming Language :: Python :: 2.7
Classifier: Programming Language :: Python :: 3
Classifier: Programming Language :: Python :: 3.4
Classifier: Programming Language :: Python :: 3.5
Classifier: Programming Language :: Python :: 3.6
Provides-Extra: dev
Provides-Extra: test
